strings_to_positions/__init__.py
strings_to_positions/positions.py
strings_to_positions/py.typed
strings_to_positions-1.1.1.dist-info/METADATA
strings_to_positions-1.1.1.dist-info/WHEEL
strings_to_positions-1.1.1.dist-info/RECORD
