Metadata-Version: 2.4
Name: strings-to-positions
Version: 1.1.1
Summary: A Python package to convert strings to positions in a source text
Author-email: Hao Luo <338265+howlowck@users.noreply.github.com>
Requires-Python: >=3.8
